{
  "version": "5",
  "dialect": "mysql",
  "id": "5414b89b-b696-4a2b-95cd-02f57aecc3ae",
  "prevId": "a77f7e5a-0281-4eaa-9617-1d5f3b87309e",
  "tables": {
    "consultas": {
      "name": "consultas",
      "columns": {
        "id": {
          "name": "id",
          "type": "varchar(255)",
          "primaryKey": false,
          "notNull": true,
          "autoincrement": false
        },
        "utente_id": {
          "name": "utente_id",
          "type": "varchar(255)",
          "primaryKey": false,
          "notNull": true,
          "autoincrement": false
        },
        "medico_id": {
          "name": "medico_id",
          "type": "varchar(255)",
          "primaryKey": false,
          "notNull": false,
          "autoincrement": false
        },
        "data_hora": {
          "name": "data_hora",
          "type": "datetime",
          "primaryKey": false,
          "notNull": true,
          "autoincrement": false
        },
        "duracao": {
          "name": "duracao",
          "type": "int",
          "primaryKey": false,
          "notNull": false,
          "autoincrement": false,
          "default": 30
        },
        "tipo_consulta": {
          "name": "tipo_consulta",
          "type": "varchar(100)",
          "primaryKey": false,
          "notNull": false,
          "autoincrement": false
        },
        "procedimento": {
          "name": "procedimento",
          "type": "text",
          "primaryKey": false,
          "notNull": false,
          "autoincrement": false
        },
        "status": {
          "name": "status",
          "type": "enum('agendada','confirmada','realizada','cancelada','faltou','em_atendimento')",
          "primaryKey": false,
          "notNull": false,
          "autoincrement": false,
          "default": "'agendada'"
        },
        "observacoes": {
          "name": "observacoes",
          "type": "text",
          "primaryKey": false,
          "notNull": false,
          "autoincrement": false
        },
        "valor_estimado": {
          "name": "valor_estimado",
          "type": "decimal(10,2)",
          "primaryKey": false,
          "notNull": false,
          "autoincrement": false
        },
        "classificacao_risco": {
          "name": "classificacao_risco",
          "type": "varchar(10)",
          "primaryKey": false,
          "notNull": false,
          "autoincrement": false
        },
        "criado_em": {
          "name": "criado_em",
          "type": "timestamp",
          "primaryKey": false,
          "notNull": false,
          "autoincrement": false,
          "default": "(now())"
        },
        "atualizado_em": {
          "name": "atualizado_em",
          "type": "timestamp",
          "primaryKey": false,
          "notNull": false,
          "autoincrement": false,
          "onUpdate": true,
          "default": "(now())"
        }
      },
      "indexes": {},
      "foreignKeys": {},
      "compositePrimaryKeys": {
        "consultas_id": {
          "name": "consultas_id",
          "columns": [
            "id"
          ]
        }
      },
      "uniqueConstraints": {},
      "checkConstraint": {}
    },
    "endodontia": {
      "name": "endodontia",
      "columns": {
        "id": {
          "name": "id",
          "type": "varchar(64)",
          "primaryKey": false,
          "notNull": true,
          "autoincrement": false
        },
        "utenteId": {
          "name": "utenteId",
          "type": "varchar(64)",
          "primaryKey": false,
          "notNull": true,
          "autoincrement": false
        },
        "numeroDente": {
          "name": "numeroDente",
          "type": "varchar(10)",
          "primaryKey": false,
          "notNull": true,
          "autoincrement": false
        },
        "numeroCanais": {
          "name": "numeroCanais",
          "type": "varchar(10)",
          "primaryKey": false,
          "notNull": true,
          "autoincrement": false
        },
        "comprimentoTrabalho": {
          "name": "comprimentoTrabalho",
          "type": "text",
          "primaryKey": false,
          "notNull": false,
          "autoincrement": false
        },
        "tecnicaInstrumentacao": {
          "name": "tecnicaInstrumentacao",
          "type": "varchar(100)",
          "primaryKey": false,
          "notNull": false,
          "autoincrement": false
        },
        "materialObturacao": {
          "name": "materialObturacao",
          "type": "varchar(100)",
          "primaryKey": false,
          "notNull": false,
          "autoincrement": false
        },
        "dataInicio": {
          "name": "dataInicio",
          "type": "varchar(10)",
          "primaryKey": false,
          "notNull": false,
          "autoincrement": false
        },
        "dataFinalizacao": {
          "name": "dataFinalizacao",
          "type": "varchar(10)",
          "primaryKey": false,
          "notNull": false,
          "autoincrement": false
        },
        "status": {
          "name": "status",
          "type": "enum('em_andamento','concluido','retratamento')",
          "primaryKey": false,
          "notNull": false,
          "autoincrement": false,
          "default": "'em_andamento'"
        },
        "observacoes": {
          "name": "observacoes",
          "type": "text",
          "primaryKey": false,
          "notNull": false,
          "autoincrement": false
        },
        "criadoEm": {
          "name": "criadoEm",
          "type": "timestamp",
          "primaryKey": false,
          "notNull": false,
          "autoincrement": false,
          "default": "(now())"
        }
      },
      "indexes": {},
      "foreignKeys": {},
      "compositePrimaryKeys": {
        "endodontia_id": {
          "name": "endodontia_id",
          "columns": [
            "id"
          ]
        }
      },
      "uniqueConstraints": {},
      "checkConstraint": {}
    },
    "imagens": {
      "name": "imagens",
      "columns": {
        "id": {
          "name": "id",
          "type": "varchar(64)",
          "primaryKey": false,
          "notNull": true,
          "autoincrement": false
        },
        "utenteId": {
          "name": "utenteId",
          "type": "varchar(64)",
          "primaryKey": false,
          "notNull": true,
          "autoincrement": false
        },
        "tipo": {
          "name": "tipo",
          "type": "enum('raio_x','fotografia','tomografia','scanner_3d','outro')",
          "primaryKey": false,
          "notNull": true,
          "autoincrement": false
        },
        "categoria": {
          "name": "categoria",
          "type": "varchar(100)",
          "primaryKey": false,
          "notNull": false,
          "autoincrement": false
        },
        "url": {
          "name": "url",
          "type": "text",
          "primaryKey": false,
          "notNull": true,
          "autoincrement": false
        },
        "nomeArquivo": {
          "name": "nomeArquivo",
          "type": "varchar(255)",
          "primaryKey": false,
          "notNull": true,
          "autoincrement": false
        },
        "tamanho": {
          "name": "tamanho",
          "type": "varchar(50)",
          "primaryKey": false,
          "notNull": false,
          "autoincrement": false
        },
        "dataImagem": {
          "name": "dataImagem",
          "type": "varchar(10)",
          "primaryKey": false,
          "notNull": false,
          "autoincrement": false
        },
        "descricao": {
          "name": "descricao",
          "type": "text",
          "primaryKey": false,
          "notNull": false,
          "autoincrement": false
        },
        "criadoEm": {
          "name": "criadoEm",
          "type": "timestamp",
          "primaryKey": false,
          "notNull": false,
          "autoincrement": false,
          "default": "(now())"
        }
      },
      "indexes": {},
      "foreignKeys": {},
      "compositePrimaryKeys": {
        "imagens_id": {
          "name": "imagens_id",
          "columns": [
            "id"
          ]
        }
      },
      "uniqueConstraints": {},
      "checkConstraint": {}
    },
    "implantes": {
      "name": "implantes",
      "columns": {
        "id": {
          "name": "id",
          "type": "varchar(64)",
          "primaryKey": false,
          "notNull": true,
          "autoincrement": false
        },
        "utenteId": {
          "name": "utenteId",
          "type": "varchar(64)",
          "primaryKey": false,
          "notNull": true,
          "autoincrement": false
        },
        "posicao": {
          "name": "posicao",
          "type": "varchar(10)",
          "primaryKey": false,
          "notNull": true,
          "autoincrement": false
        },
        "marca": {
          "name": "marca",
          "type": "varchar(100)",
          "primaryKey": false,
          "notNull": false,
          "autoincrement": false
        },
        "modelo": {
          "name": "modelo",
          "type": "varchar(100)",
          "primaryKey": false,
          "notNull": false,
          "autoincrement": false
        },
        "diametro": {
          "name": "diametro",
          "type": "varchar(20)",
          "primaryKey": false,
          "notNull": false,
          "autoincrement": false
        },
        "comprimento": {
          "name": "comprimento",
          "type": "varchar(20)",
          "primaryKey": false,
          "notNull": false,
          "autoincrement": false
        },
        "lote": {
          "name": "lote",
          "type": "varchar(50)",
          "primaryKey": false,
          "notNull": false,
          "autoincrement": false
        },
        "dataColocacao": {
          "name": "dataColocacao",
          "type": "varchar(10)",
          "primaryKey": false,
          "notNull": false,
          "autoincrement": false
        },
        "dataCarga": {
          "name": "dataCarga",
          "type": "varchar(10)",
          "primaryKey": false,
          "notNull": false,
          "autoincrement": false
        },
        "tipoProtese": {
          "name": "tipoProtese",
          "type": "varchar(100)",
          "primaryKey": false,
          "notNull": false,
          "autoincrement": false
        },
        "status": {
          "name": "status",
          "type": "enum('planejado','colocado','osseointegrado','protese_instalada','falha')",
          "primaryKey": false,
          "notNull": false,
          "autoincrement": false,
          "default": "'planejado'"
        },
        "observacoes": {
          "name": "observacoes",
          "type": "text",
          "primaryKey": false,
          "notNull": false,
          "autoincrement": false
        },
        "criadoEm": {
          "name": "criadoEm",
          "type": "timestamp",
          "primaryKey": false,
          "notNull": false,
          "autoincrement": false,
          "default": "(now())"
        }
      },
      "indexes": {},
      "foreignKeys": {},
      "compositePrimaryKeys": {
        "implantes_id": {
          "name": "implantes_id",
          "columns": [
            "id"
          ]
        }
      },
      "uniqueConstraints": {},
      "checkConstraint": {}
    },
    "laboratorio": {
      "name": "laboratorio",
      "columns": {
        "id": {
          "name": "id",
          "type": "varchar(64)",
          "primaryKey": false,
          "notNull": true,
          "autoincrement": false
        },
        "utenteId": {
          "name": "utenteId",
          "type": "varchar(64)",
          "primaryKey": false,
          "notNull": true,
          "autoincrement": false
        },
        "tipoTrabalho": {
          "name": "tipoTrabalho",
          "type": "varchar(100)",
          "primaryKey": false,
          "notNull": true,
          "autoincrement": false
        },
        "dentes": {
          "name": "dentes",
          "type": "varchar(255)",
          "primaryKey": false,
          "notNull": false,
          "autoincrement": false
        },
        "laboratorioNome": {
          "name": "laboratorioNome",
          "type": "varchar(200)",
          "primaryKey": false,
          "notNull": false,
          "autoincrement": false
        },
        "cor": {
          "name": "cor",
          "type": "varchar(50)",
          "primaryKey": false,
          "notNull": false,
          "autoincrement": false
        },
        "material": {
          "name": "material",
          "type": "varchar(100)",
          "primaryKey": false,
          "notNull": false,
          "autoincrement": false
        },
        "dataEnvio": {
          "name": "dataEnvio",
          "type": "varchar(10)",
          "primaryKey": false,
          "notNull": false,
          "autoincrement": false
        },
        "dataPrevisao": {
          "name": "dataPrevisao",
          "type": "varchar(10)",
          "primaryKey": false,
          "notNull": false,
          "autoincrement": false
        },
        "dataRecepcao": {
          "name": "dataRecepcao",
          "type": "varchar(10)",
          "primaryKey": false,
          "notNull": false,
          "autoincrement": false
        },
        "dataInstalacao": {
          "name": "dataInstalacao",
          "type": "varchar(10)",
          "primaryKey": false,
          "notNull": false,
          "autoincrement": false
        },
        "custo": {
          "name": "custo",
          "type": "varchar(20)",
          "primaryKey": false,
          "notNull": false,
          "autoincrement": false
        },
        "status": {
          "name": "status",
          "type": "enum('pendente','enviado','em_producao','recebido','instalado','ajuste_necessario')",
          "primaryKey": false,
          "notNull": false,
          "autoincrement": false,
          "default": "'pendente'"
        },
        "observacoes": {
          "name": "observacoes",
          "type": "text",
          "primaryKey": false,
          "notNull": false,
          "autoincrement": false
        },
        "criadoEm": {
          "name": "criadoEm",
          "type": "timestamp",
          "primaryKey": false,
          "notNull": false,
          "autoincrement": false,
          "default": "(now())"
        }
      },
      "indexes": {},
      "foreignKeys": {},
      "compositePrimaryKeys": {
        "laboratorio_id": {
          "name": "laboratorio_id",
          "columns": [
            "id"
          ]
        }
      },
      "uniqueConstraints": {},
      "checkConstraint": {}
    },
    "odontograma": {
      "name": "odontograma",
      "columns": {
        "id": {
          "name": "id",
          "type": "varchar(64)",
          "primaryKey": false,
          "notNull": true,
          "autoincrement": false
        },
        "utenteId": {
          "name": "utenteId",
          "type": "varchar(64)",
          "primaryKey": false,
          "notNull": true,
          "autoincrement": false
        },
        "numeroDente": {
          "name": "numeroDente",
          "type": "varchar(10)",
          "primaryKey": false,
          "notNull": true,
          "autoincrement": false
        },
        "faces": {
          "name": "faces",
          "type": "text",
          "primaryKey": false,
          "notNull": false,
          "autoincrement": false
        },
        "condicao": {
          "name": "condicao",
          "type": "varchar(100)",
          "primaryKey": false,
          "notNull": false,
          "autoincrement": false
        },
        "tratamento": {
          "name": "tratamento",
          "type": "varchar(100)",
          "primaryKey": false,
          "notNull": false,
          "autoincrement": false
        },
        "observacoes": {
          "name": "observacoes",
          "type": "text",
          "primaryKey": false,
          "notNull": false,
          "autoincrement": false
        },
        "dataRegistro": {
          "name": "dataRegistro",
          "type": "varchar(10)",
          "primaryKey": false,
          "notNull": false,
          "autoincrement": false
        },
        "criadoEm": {
          "name": "criadoEm",
          "type": "timestamp",
          "primaryKey": false,
          "notNull": false,
          "autoincrement": false,
          "default": "(now())"
        }
      },
      "indexes": {},
      "foreignKeys": {},
      "compositePrimaryKeys": {
        "odontograma_id": {
          "name": "odontograma_id",
          "columns": [
            "id"
          ]
        }
      },
      "uniqueConstraints": {},
      "checkConstraint": {}
    },
    "ortodontia": {
      "name": "ortodontia",
      "columns": {
        "id": {
          "name": "id",
          "type": "varchar(64)",
          "primaryKey": false,
          "notNull": true,
          "autoincrement": false
        },
        "utenteId": {
          "name": "utenteId",
          "type": "varchar(64)",
          "primaryKey": false,
          "notNull": true,
          "autoincrement": false
        },
        "tipoAparelho": {
          "name": "tipoAparelho",
          "type": "varchar(100)",
          "primaryKey": false,
          "notNull": false,
          "autoincrement": false
        },
        "dataInicio": {
          "name": "dataInicio",
          "type": "varchar(10)",
          "primaryKey": false,
          "notNull": false,
          "autoincrement": false
        },
        "dataPrevisaoTermino": {
          "name": "dataPrevisaoTermino",
          "type": "varchar(10)",
          "primaryKey": false,
          "notNull": false,
          "autoincrement": false
        },
        "status": {
          "name": "status",
          "type": "enum('ativo','concluido','pausado')",
          "primaryKey": false,
          "notNull": false,
          "autoincrement": false,
          "default": "'ativo'"
        },
        "observacoes": {
          "name": "observacoes",
          "type": "text",
          "primaryKey": false,
          "notNull": false,
          "autoincrement": false
        },
        "criadoEm": {
          "name": "criadoEm",
          "type": "timestamp",
          "primaryKey": false,
          "notNull": false,
          "autoincrement": false,
          "default": "(now())"
        }
      },
      "indexes": {},
      "foreignKeys": {},
      "compositePrimaryKeys": {
        "ortodontia_id": {
          "name": "ortodontia_id",
          "columns": [
            "id"
          ]
        }
      },
      "uniqueConstraints": {},
      "checkConstraint": {}
    },
    "ortodontia_consultas": {
      "name": "ortodontia_consultas",
      "columns": {
        "id": {
          "name": "id",
          "type": "varchar(64)",
          "primaryKey": false,
          "notNull": true,
          "autoincrement": false
        },
        "ortodontiaId": {
          "name": "ortodontiaId",
          "type": "varchar(64)",
          "primaryKey": false,
          "notNull": true,
          "autoincrement": false
        },
        "dataConsulta": {
          "name": "dataConsulta",
          "type": "varchar(10)",
          "primaryKey": false,
          "notNull": true,
          "autoincrement": false
        },
        "procedimentos": {
          "name": "procedimentos",
          "type": "text",
          "primaryKey": false,
          "notNull": false,
          "autoincrement": false
        },
        "observacoes": {
          "name": "observacoes",
          "type": "text",
          "primaryKey": false,
          "notNull": false,
          "autoincrement": false
        },
        "proximaConsulta": {
          "name": "proximaConsulta",
          "type": "varchar(10)",
          "primaryKey": false,
          "notNull": false,
          "autoincrement": false
        },
        "criadoEm": {
          "name": "criadoEm",
          "type": "timestamp",
          "primaryKey": false,
          "notNull": false,
          "autoincrement": false,
          "default": "(now())"
        }
      },
      "indexes": {},
      "foreignKeys": {},
      "compositePrimaryKeys": {
        "ortodontia_consultas_id": {
          "name": "ortodontia_consultas_id",
          "columns": [
            "id"
          ]
        }
      },
      "uniqueConstraints": {},
      "checkConstraint": {}
    },
    "periodontograma": {
      "name": "periodontograma",
      "columns": {
        "id": {
          "name": "id",
          "type": "varchar(64)",
          "primaryKey": false,
          "notNull": true,
          "autoincrement": false
        },
        "utenteId": {
          "name": "utenteId",
          "type": "varchar(64)",
          "primaryKey": false,
          "notNull": true,
          "autoincrement": false
        },
        "numeroDente": {
          "name": "numeroDente",
          "type": "varchar(10)",
          "primaryKey": false,
          "notNull": true,
          "autoincrement": false
        },
        "medicoes": {
          "name": "medicoes",
          "type": "text",
          "primaryKey": false,
          "notNull": true,
          "autoincrement": false
        },
        "dataAvaliacao": {
          "name": "dataAvaliacao",
          "type": "varchar(10)",
          "primaryKey": false,
          "notNull": true,
          "autoincrement": false
        },
        "criadoEm": {
          "name": "criadoEm",
          "type": "timestamp",
          "primaryKey": false,
          "notNull": false,
          "autoincrement": false,
          "default": "(now())"
        }
      },
      "indexes": {},
      "foreignKeys": {},
      "compositePrimaryKeys": {
        "periodontograma_id": {
          "name": "periodontograma_id",
          "columns": [
            "id"
          ]
        }
      },
      "uniqueConstraints": {},
      "checkConstraint": {}
    },
    "prescricoes": {
      "name": "prescricoes",
      "columns": {
        "id": {
          "name": "id",
          "type": "varchar(64)",
          "primaryKey": false,
          "notNull": true,
          "autoincrement": false
        },
        "utenteId": {
          "name": "utenteId",
          "type": "varchar(64)",
          "primaryKey": false,
          "notNull": true,
          "autoincrement": false
        },
        "dataPrescricao": {
          "name": "dataPrescricao",
          "type": "varchar(10)",
          "primaryKey": false,
          "notNull": true,
          "autoincrement": false
        },
        "medicamentos": {
          "name": "medicamentos",
          "type": "text",
          "primaryKey": false,
          "notNull": true,
          "autoincrement": false
        },
        "diagnostico": {
          "name": "diagnostico",
          "type": "text",
          "primaryKey": false,
          "notNull": false,
          "autoincrement": false
        },
        "observacoes": {
          "name": "observacoes",
          "type": "text",
          "primaryKey": false,
          "notNull": false,
          "autoincrement": false
        },
        "criadoEm": {
          "name": "criadoEm",
          "type": "timestamp",
          "primaryKey": false,
          "notNull": false,
          "autoincrement": false,
          "default": "(now())"
        }
      },
      "indexes": {},
      "foreignKeys": {},
      "compositePrimaryKeys": {
        "prescricoes_id": {
          "name": "prescricoes_id",
          "columns": [
            "id"
          ]
        }
      },
      "uniqueConstraints": {},
      "checkConstraint": {}
    },
    "users": {
      "name": "users",
      "columns": {
        "id": {
          "name": "id",
          "type": "varchar(64)",
          "primaryKey": false,
          "notNull": true,
          "autoincrement": false
        },
        "name": {
          "name": "name",
          "type": "text",
          "primaryKey": false,
          "notNull": false,
          "autoincrement": false
        },
        "email": {
          "name": "email",
          "type": "varchar(320)",
          "primaryKey": false,
          "notNull": false,
          "autoincrement": false
        },
        "loginMethod": {
          "name": "loginMethod",
          "type": "varchar(64)",
          "primaryKey": false,
          "notNull": false,
          "autoincrement": false
        },
        "role": {
          "name": "role",
          "type": "enum('user','admin')",
          "primaryKey": false,
          "notNull": true,
          "autoincrement": false,
          "default": "'user'"
        },
        "createdAt": {
          "name": "createdAt",
          "type": "timestamp",
          "primaryKey": false,
          "notNull": false,
          "autoincrement": false,
          "default": "(now())"
        },
        "lastSignedIn": {
          "name": "lastSignedIn",
          "type": "timestamp",
          "primaryKey": false,
          "notNull": false,
          "autoincrement": false,
          "default": "(now())"
        }
      },
      "indexes": {},
      "foreignKeys": {},
      "compositePrimaryKeys": {
        "users_id": {
          "name": "users_id",
          "columns": [
            "id"
          ]
        }
      },
      "uniqueConstraints": {},
      "checkConstraint": {}
    },
    "utentes": {
      "name": "utentes",
      "columns": {
        "id": {
          "name": "id",
          "type": "varchar(36)",
          "primaryKey": false,
          "notNull": true,
          "autoincrement": false
        },
        "numeroUtente": {
          "name": "numeroUtente",
          "type": "varchar(20)",
          "primaryKey": false,
          "notNull": true,
          "autoincrement": false
        },
        "nomeCompleto": {
          "name": "nomeCompleto",
          "type": "varchar(200)",
          "primaryKey": false,
          "notNull": true,
          "autoincrement": false
        },
        "dataNascimento": {
          "name": "dataNascimento",
          "type": "varchar(10)",
          "primaryKey": false,
          "notNull": true,
          "autoincrement": false
        },
        "genero": {
          "name": "genero",
          "type": "enum('M','F','Outro')",
          "primaryKey": false,
          "notNull": true,
          "autoincrement": false
        },
        "nif": {
          "name": "nif",
          "type": "varchar(9)",
          "primaryKey": false,
          "notNull": false,
          "autoincrement": false
        },
        "numUtenteSns": {
          "name": "numUtenteSns",
          "type": "varchar(9)",
          "primaryKey": false,
          "notNull": false,
          "autoincrement": false
        },
        "fotoPerfil": {
          "name": "fotoPerfil",
          "type": "text",
          "primaryKey": false,
          "notNull": false,
          "autoincrement": false
        },
        "contacto": {
          "name": "contacto",
          "type": "text",
          "primaryKey": false,
          "notNull": false,
          "autoincrement": false
        },
        "morada": {
          "name": "morada",
          "type": "text",
          "primaryKey": false,
          "notNull": false,
          "autoincrement": false
        },
        "infoMedica": {
          "name": "infoMedica",
          "type": "text",
          "primaryKey": false,
          "notNull": true,
          "autoincrement": false
        },
        "status": {
          "name": "status",
          "type": "enum('ativo','inativo','arquivado')",
          "primaryKey": false,
          "notNull": true,
          "autoincrement": false,
          "default": "'ativo'"
        },
        "tags": {
          "name": "tags",
          "type": "text",
          "primaryKey": false,
          "notNull": false,
          "autoincrement": false
        },
        "criadoPor": {
          "name": "criadoPor",
          "type": "varchar(64)",
          "primaryKey": false,
          "notNull": true,
          "autoincrement": false
        },
        "criadoEm": {
          "name": "criadoEm",
          "type": "timestamp",
          "primaryKey": false,
          "notNull": false,
          "autoincrement": false,
          "default": "(now())"
        },
        "atualizadoEm": {
          "name": "atualizadoEm",
          "type": "timestamp",
          "primaryKey": false,
          "notNull": false,
          "autoincrement": false,
          "onUpdate": true,
          "default": "(now())"
        }
      },
      "indexes": {},
      "foreignKeys": {},
      "compositePrimaryKeys": {
        "utentes_id": {
          "name": "utentes_id",
          "columns": [
            "id"
          ]
        }
      },
      "uniqueConstraints": {
        "utentes_numeroUtente_unique": {
          "name": "utentes_numeroUtente_unique",
          "columns": [
            "numeroUtente"
          ]
        }
      },
      "checkConstraint": {}
    }
  },
  "views": {},
  "_meta": {
    "schemas": {},
    "tables": {},
    "columns": {}
  },
  "internal": {
    "tables": {},
    "indexes": {}
  }
}